README.md
setup.cfg
setup.py
b2fuse/__init__.py
b2fuse/b2fuse.py
b2fuse/b2fuse_main.py
b2fuse/cached_bucket.py
b2fuse/directory_structure.py
b2fuse/tier1_tests.py
b2fuse/utility.py
b2fuse.egg-info/PKG-INFO
b2fuse.egg-info/SOURCES.txt
b2fuse.egg-info/dependency_links.txt
b2fuse.egg-info/entry_points.txt
b2fuse.egg-info/requires.txt
b2fuse.egg-info/top_level.txt
b2fuse.egg-info/zip-safe
b2fuse/filetypes/B2BaseFile.py
b2fuse/filetypes/B2FileDisk.py
b2fuse/filetypes/B2HashFile.py
b2fuse/filetypes/B2SequentialFileMemory.py
b2fuse/filetypes/B2SparseFileMemory.py
b2fuse/filetypes/__init__.py