Metadata-Version: 1.1
Name: b2fuse
Version: 1.3
Summary: FUSE integration for Backblaze B2 Cloud storage
Home-page: UNKNOWN
Author: Sondre Engebraaten
Author-email: info@sender.com
License: UNKNOWN
Platform: UNKNOWN
Classifier: Programming Language :: Python :: 2
Classifier: Programming Language :: Python :: 2.7
